djangocms_mapycz_markers/__init__.py
djangocms_mapycz_markers/actions.py
djangocms_mapycz_markers/cms_plugins.py
djangocms_mapycz_markers/models.py
djangocms_mapycz_markers/urls.py
djangocms_mapycz_markers/utils.py
djangocms_mapycz_markers/utils_admin.py
djangocms_mapycz_markers/locale/cs/LC_MESSAGES/django.mo
djangocms_mapycz_markers/locale/cs/LC_MESSAGES/django.po
djangocms_mapycz_markers/locale/cs/LC_MESSAGES/djangojs.mo
djangocms_mapycz_markers/locale/cs/LC_MESSAGES/djangojs.po
djangocms_mapycz_markers/migrations/0001_initial.py
djangocms_mapycz_markers/migrations/__init__.py
djangocms_mapycz_markers/static/djangocms_mapycz_markers/js/admin-form.js
djangocms_mapycz_markers/static/djangocms_mapycz_markers/js/connector.js
djangocms_mapycz_markers/static/djangocms_mapycz_markers/js/map.js
djangocms_mapycz_markers/templates/djangocms_mapycz_markers/connector.html
djangocms_mapycz_markers/templates/djangocms_mapycz_markers/map.html
djangocms_mapycz_markers/templates/djangocms_mapycz_markers/marker.html
djangocms_mapycz_markers/templates/djangocms_mapycz_markers/marker_admin_form.html
example/__init__.py
example/manage.py
tests/__init__.py
tests/settings.py
tests/test_cms_plugins.py
tests/test_models.py
tests/test_utils.py
tests/urls.py
djangocms_mapycz_markers-1.1.0.dist-info/METADATA
djangocms_mapycz_markers-1.1.0.dist-info/WHEEL
djangocms_mapycz_markers-1.1.0.dist-info/top_level.txt
djangocms_mapycz_markers-1.1.0.dist-info/RECORD
