Metadata-Version: 2.1
Name: djangocms-mapycz-markers
Version: 1.1.0
Summary: DjangoCMS Mapy.cz Markers
Author: Zdeněk Böhm
Author-email: zdenek.bohm@nic.cz
License: GPLv3+
Classifier: Typing :: Typed
Classifier: Programming Language :: Python
Classifier: Programming Language :: Python :: 3.8
Classifier: Programming Language :: Python :: 3.9
Classifier: Programming Language :: Python :: 3.10
Classifier: Framework :: Django CMS :: 3.7
Requires-Python: >=3.8
Provides-Extra: quality
Requires-Dist: doc8 ; extra == 'quality'
Requires-Dist: flake8 ; extra == 'quality'
Requires-Dist: isort ; extra == 'quality'
Requires-Dist: mypy ; extra == 'quality'
Requires-Dist: pydocstyle ; extra == 'quality'
Provides-Extra: test
Requires-Dist: responses ; extra == 'test'
Provides-Extra: types
Requires-Dist: types-requests ; extra == 'types'
